setup.py
giscegisplot/__init__.py
giscegisplot/plot.py
giscegisplot.egg-info/PKG-INFO
giscegisplot.egg-info/SOURCES.txt
giscegisplot.egg-info/dependency_links.txt
giscegisplot.egg-info/entry_points.txt
giscegisplot.egg-info/requires.txt
giscegisplot.egg-info/top_level.txt