Metadata-Version: 2.1
Name: giscegisplot
Version: 0.2.2
Summary: Plot geoms over OSM
Home-page: http://git.gisce.net/gis/giscegisplot
Author: GISCE-TI, S.L.
Author-email: devel@gisce.net
License: MIT
